{
    "OS": "mac",
    "soft": {
        "uninstall": {
            "g++": {
                "name": "g++",
                "version": "3.20",
                "drive": "default",
                "shell": ""
            }
        },
        "install": {
            "g++": {
                "name": "g++",
                "version": "3.20",
                "drive": "default",
                "shell": ""
            }
        },
        "xinstall": {
            "brew": {
                "name": "brew",
                "version": "",
                "drive": "shell",
                "shell": "/bin/bash -c \"$(curl -fsSL https://raw.githubusercontent.com/Homebrew/install/HEAD/install.sh)\""
            },
            "git": {
                "name": "git",
                "version": "3.20",
                "drive": "default",
                "shell": ""
            },
            "g++": {
                "name": "g++",
                "version": "3.20",
                "drive": "default",
                "shell": ""
            },
            "gcc": {
                "name": "gcc",
                "version": "3.20",
                "drive": "default",
                "shell": ""
            },
            "make": {
                "name": "make",
                "version": "3.20",
                "drive": "default",
                "shell": ""
            },
            "cmake": {
                "name": "cmake",
                "version": "3.20",
                "drive": "default",
                "shell": ""
            },
            "python3": {
                "name": "python3",
                "version": "3.20",
                "drive": "default",
                "shell": ""
            },
            "rust": {
                "name": "python3",
                "version": "3.20",
                "drive": "default",
                "shell": ""
            }
        }
    },
    "code": {
        "LeetCode": {
            "local_path": "/home/Code/github",
            "project_name": "LeetCode",
            "branch": "master",
            "github_url": "https://github.com/liupengzhouyi/LeetCode.git",
            "git_url": "https://github.com/liupengzhouyi/LeetCode.git",
            "source": "github"
        },
        "cassel-college.github.io": {
            "local_path": "/home/Code/github",
            "project_name": "cassel-college.github.io",
            "branch": "master",
            "github_url": "https://github.com/liupengzhouyi/cassel-college.github.io.git",
            "git_url": "https://github.com/liupengzhouyi/cassel-college.github.io.git",
            "source": "github"
        },
        "mongoliacavalry.github.io.git": {
            "local_path": "/home/Code/github",
            "project_name": "mongoliacavalry.github.io",
            "branch": "master",
            "github_url": "https://github.com/liupengzhouyi/mongoliacavalry.github.io.git",
            "git_url": "https://github.com/liupengzhouyi/mongoliacavalry.github.io.git",
            "source": "github"
        },
        "Math": {
            "local_path": "/home/Code/github",
            "project_name": "Math",
            "branch": "master",
            "github_url": "https://github.com/liupengzhouyi/Math.git",
            "git_url": "https://github.com/liupengzhouyi/Math.git",
            "source": "github"
        }
    },
    "remove_code": {
        "LeetCode": {
            "local_path": "/home/Code/github",
            "project_name": "LeetCode",
            "branch": "master",
            "github_url": "https://github.com/liupengzhouyi/LeetCode.git",
            "git_url": "https://github.com/liupengzhouyi/LeetCode.git",
            "source": "github"
        }
    },
    "python-package": {
        "name": {
            "package_name": "",
            "version": "",
            "python_version": ""
        }
    }
}